convector/__init__.py
convector/cli.py
convector/convector.py
convector/core/__init__.py
convector/core/base_file_handler.py
convector/core/convector_config.py
convector/core/directory_processor.py
convector/core/file_handler_factory.py
convector/core/profile.py
convector/core/user_interaction.py
convector/data_processors/__init__.py
convector/data_processors/data_processors.py
convector/file_handlers/__init__.py
convector/file_handlers/csv_file_handler.py
convector/file_handlers/json_file_handler.py
convector/file_handlers/json_gz_file_handler.py
convector/file_handlers/jsonl_file_handler.py
convector/file_handlers/parquet_file_handler.py
convector/file_handlers/txt_file_handler.py
convector/file_handlers/zst_file_handler.py
convector/utils/__init__.py
convector/utils/label_filter.py
convector/utils/output_schema_handler.py
convector/utils/random_selector.py
convector-0.1.1.dist-info/LICENSE
convector-0.1.1.dist-info/METADATA
convector-0.1.1.dist-info/WHEEL
convector-0.1.1.dist-info/entry_points.txt
convector-0.1.1.dist-info/top_level.txt
convector-0.1.1.dist-info/RECORD
