Metadata-Version: 2.1
Name: convector
Version: 0.1.1
Summary: A tool for transforming conversational data to a unified format
Home-page: https://github.com/teilomillet/convector
Author: Teïlo Millet
Author-email: teilomillet@proton.me
Project-URL: Bug Reports, https://github.com/teilomillet/convector/issues
Project-URL: Source, https://github.com/teilomillet/convector/
Keywords: conversational data transformation
Classifier: Development Status :: 3 - Alpha
Classifier: Intended Audience :: Developers
Classifier: Topic :: Software Development :: Build Tools
Classifier: License :: OSI Approved :: MIT License
Classifier: Programming Language :: Python :: 3
Classifier: Programming Language :: Python :: 3.9
Classifier: Programming Language :: Python :: 3.10
Classifier: Programming Language :: Python :: 3.11
Requires-Python: >=3.6, <4
License-File: LICENSE
Requires-Dist: tqdm
Requires-Dist: pandas
Requires-Dist: zstandard
